CHANGES.txt
LICENSE.txt
MANIFEST.in
README.md
pyproject.toml
requirements.txt
setup.py
test-requirements.txt
c/generic-parser.c
c/generic-parser.h
c/native_openmx.c
c/native_qe.c
dfttools/__init__.py
dfttools/data.py
dfttools/formatters.py
dfttools/presentation.py
dfttools/simple.py
dfttools/types.py
dfttools/util.py
dfttools.egg-info/PKG-INFO
dfttools.egg-info/SOURCES.txt
dfttools.egg-info/dependency_links.txt
dfttools.egg-info/requires.txt
dfttools.egg-info/top_level.txt
dfttools/parsers/__init__.py
dfttools/parsers/elk.py
dfttools/parsers/generic.py
dfttools/parsers/materialsproject.py
dfttools/parsers/openmx.py
dfttools/parsers/qe.py
dfttools/parsers/structure.py
dfttools/parsers/tools.py
dfttools/parsers/vasp.py
dfttools/parsers/wannier90.py
scripts/dft-materialsproject
scripts/dft-plot-bands
scripts/dft-svg-structure
scripts/dft-xcrysden