Metadata-Version: 2.1
Name: dfttools
Version: 0.1.0
Summary: Tools for parsing textual data from modern DFT (quantum chemistry) packages
Home-page: https://github.com/pulkin/dfttools
Author: Artem Pulkin
Author-email: gpulkin@gmail.com
License: LICENSE.txt
Platform: UNKNOWN
License-File: LICENSE.txt
